freshpointcli/README.md
freshpointcli/__init__.py
freshpointcli/__main__.py
freshpointcli/files.py
freshpointcli/logger.py
freshpointcli/py.typed
freshpointcli/promt/__init__.py
freshpointcli/promt/completers.py
freshpointcli/promt/lexers.py
freshpointcli/promt/parsers.py
freshpointcli/promt/processor.py
freshpointcli/promt/styles.py
freshpointcli/promt/tables.py
FreshPointCLI-0.2.0.dist-info/LICENSE
FreshPointCLI-0.2.0.dist-info/METADATA
FreshPointCLI-0.2.0.dist-info/WHEEL
FreshPointCLI-0.2.0.dist-info/entry_points.txt
FreshPointCLI-0.2.0.dist-info/top_level.txt
FreshPointCLI-0.2.0.dist-info/RECORD
