Metadata-Version: 2.1
Name: FreshPointCLI
Version: 0.2.0
Summary: FreshPoint webpage CLI interface.
Author-email: Konstantin Mykhailov <constantinemykhailov@gmail.com>
License: MIT License
Project-URL: Homepage, https://github.com/mykhakos/FreshPointCLI
Keywords: freshpoint,freshpoint.cz
Classifier: Development Status :: 3 - Alpha
Classifier: Environment :: Console
Classifier: Intended Audience :: End Users/Desktop
Classifier: Intended Audience :: Other Audience
Classifier: License :: OSI Approved :: MIT License
Classifier: Natural Language :: English
Classifier: Natural Language :: Czech
Classifier: Operating System :: OS Independent
Classifier: Programming Language :: Python :: 3
Classifier: Programming Language :: Python :: 3 :: Only
Classifier: Programming Language :: Python :: 3.8
Classifier: Programming Language :: Python :: 3.9
Classifier: Programming Language :: Python :: 3.10
Classifier: Programming Language :: Python :: 3.11
Classifier: Programming Language :: Python :: 3.12
Classifier: Topic :: Internet
Classifier: Topic :: Other/Nonlisted Topic
Classifier: Topic :: Terminals
Classifier: Topic :: Text Processing
Classifier: Topic :: Text Processing :: Markup :: HTML
Classifier: Topic :: Utilities
Classifier: Typing :: Typed
Requires-Python: >=3.8
License-File: LICENSE
Requires-Dist: platformdirs >=3.5.3
Requires-Dist: prompt-toolkit >=3.0.40
Requires-Dist: pydantic >=2.0
Requires-Dist: pygments >=2.17.0
Requires-Dist: rich >=13.6.0
Requires-Dist: unidecode >=1.1.0
Requires-Dist: freshpointsync ==0.2.1
Provides-Extra: build
Requires-Dist: build ; extra == 'build'
Requires-Dist: twine ; extra == 'build'
Provides-Extra: dev
Requires-Dist: tox ; extra == 'dev'
Requires-Dist: freshpointsync[lint] ; extra == 'dev'
Requires-Dist: freshpointsync[test] ; extra == 'dev'
Requires-Dist: freshpointsync[build] ; extra == 'dev'
Provides-Extra: lint
Requires-Dist: mypy ; extra == 'lint'
Requires-Dist: ruff ; extra == 'lint'
Provides-Extra: test
Requires-Dist: pytest ; extra == 'test'
Requires-Dist: pytest-asyncio ; extra == 'test'
